{
    "Startup": {
        "recognition": {
            "type": "OCR",
            "param": {
                "expected": "选择自定义语言"
            }
        },
        "action": {
            "type": "Click",
            "param": {
                "target": [
                    575,
                    538,
                    230,
                    59
                ]
            }
        }
    },
    "ClaimRewards": {
        "next": [
            "Back2Main"
        ]
    },
    "Back2Main": {
        "recognition": {
            "type": "TemplateMatch",
            "param": {
                "template": "Season7Banner.png"
            }
        },
        "next": [
            "ClickSeasonBanner"
        ]
    },
    "ClickSeasonBanner": {
        "recognition": {
            "type": "TemplateMatch",
            "param": {
                "template": "Season7Banner.png"
            }
        },
        "action": {
            "type": "Click",
            "param": {
                "target": true
            }
        },
        "next": [
            "WaitSwitch2SeasonScence"
        ],
        "post_delay": 500
    },
    "WaitSwitch2SeasonScence": {
        "recognition": {
            "type": "OCR",
            "param": {
                "expected": [
                    "战斗通行证",
                    "通行证任务"
                ]
            }
        },
        "next": [
            "ClickOnMission"
        ]
    },
    "ClickOnMission": {
        "recognition": {
            "type": "OCR",
            "param": {
                "expected": [
                    "通行证任务"
                ]
            }
        },
        "action": {
            "type": "Click",
            "param": {
                "target": true
            }
        },
        "next": [
            "WaitForMissionList"
        ]
    },
    "WaitForMissionList": {
        "recognition": {
            "type": "TemplateMatch",
            "param": {
                "template": [
                    "TitleDailyMission.png",
                    "TitleWeekyMission.png"
                ]
            }
        },
        "next": [
            "ClaimDailyRewards"
        ]
    },
    "ClaimDailyRewards": {
        "recognition": {
            "type": "TemplateMatch",
            "param": {
                "template": [
                    "TitleDailyMission.png"
                ]
            }
        },
        "action": {
            "type": "Click",
            "param": {
                "target": true
            }
        },
        "next": [
            "RewardSlot1"
        ]
    },
    "ClaimWeeklyRewards": {
        "recognition": {
            "type": "TemplateMatch",
            "param": {
                "template": [
                    "TitleWeekyMission.png"
                ]
            }
        },
        "action": {
            "type": "Click",
            "param": {
                "target": [
                    277,
                    359,
                    20,
                    85
                ]
            }
        },
        "next": [
            "RewardSlot1"
        ]
    },
    "RewardSlot1": {
        "recognition": {
            "type": "DirectHit"
        },
        "action": {
            "type": "Click",
            "param": {
                "target": [
                    383,
                    194,
                    330,
                    52
                ]
            }
        },
        "next": [
            "RewardSlot2"
        ]
    },
    "RewardSlot2": {
        "recognition": {
            "type": "DirectHit"
        },
        "action": {
            "type": "Click",
            "param": {
                "target": [
                    387,
                    286,
                    337,
                    52
                ]
            }
        },
        "next": [
            "RewardSlot3"
        ]
    },
    "RewardSlot3": {
        "recognition": {
            "type": "DirectHit"
        },
        "action": {
            "type": "Click",
            "param": {
                "target": [
                    380,
                    377,
                    339,
                    56
                ]
            }
        },
        "next": [
            "RewardSlot4"
        ]
    },
    "RewardSlot4": {
        "recognition": {
            "type": "DirectHit"
        },
        "action": {
            "type": "Click",
            "param": {
                "target": [
                    377,
                    468,
                    343,
                    57
                ]
            }
        },
        "next": [
            "RewardSlot5Daily"
        ]
    },
    "RewardSlot5Daily": {
        "recognition": {
            "type": "DirectHit"
        },
        "action": {
            "type": "Click",
            "param": {
                "target": [
                    377,
                    560,
                    340,
                    56
                ]
            }
        },
        "next": [
            "ClaimWeeklyRewards"
        ]
    },
    "RewardSlot5Weekly": {
        "recognition": {
            "type": "DirectHit"
        },
        "action": {
            "type": "Click",
            "param": {
                "target": [
                    377,
                    560,
                    340,
                    56
                ]
            }
        }
    },
    "ToEnkephalin": {
        "next": [
            "ClickEnkephalin"
        ]
    },
    "WaitForEnkephalinScence": {
        "recognition": {
            "type": "OCR",
            "param": {
                "expected": [
                    "补充脑啡肽"
                ]
            }
        },
        "next": [
            "TopupEnkephalin",
            "GoBack2Main"
        ]
    },
    "ClickEnkephalin": {
        "recognition": {
            "type": "DirectHit"
        },
        "action": {
            "type": "Click",
            "param": {
                "target": [
                    351,
                    632,
                    128,
                    39
                ]
            }
        },
        "next": [
            "WaitForEnkephalinScence"
        ]
    },
    "TopupEnkephalin": {
        "recognition": {
            "type": "ColorMatch",
            "param": {
                "upper": [
                    163,
                    138,
                    112
                ],
                "lower": [
                    143,
                    118,
                    92
                ],
                "roi": [
                    840,
                    313,
                    31,
                    28
                ]
            }
        },
        "action": {
            "type": "Click",
            "param": {
                "target": true
            }
        },
        "next": [
            "ConfirmTopup"
        ]
    },
    "ConfirmTopup": {
        "recognition": {
            "type": "TemplateMatch",
            "param": {
                "template": [
                    "ComfirmTopup.png"
                ]
            }
        },
        "action": {
            "type": "Click",
            "param": {
                "target": true
            }
        },
        "next": [
            "GoBack2Main"
        ]
    },
    "GoBack2Main": {
        "recognition": "OCR",
        "expected": [
            "脑啡肽不足"
        ],
        "action": "Click",
        "target": [
            79,
            44,
            55,
            26
        ],
        "focus": {
            "Node.Recognition.Succeeded": "脑啡肽不足，返回主界面"
        }
    }
}